lusid_notification/__init__.py
lusid_notification/__version__.py
lusid_notification/api_client.py
lusid_notification/configuration.py
lusid_notification/exceptions.py
lusid_notification/rest.py
lusid_notification/api/__init__.py
lusid_notification/api/application_metadata_api.py
lusid_notification/api/deliveries_api.py
lusid_notification/api/event_types_api.py
lusid_notification/api/manual_event_api.py
lusid_notification/api/notifications_api.py
lusid_notification/api/subscriptions_api.py
lusid_notification/models/__init__.py
lusid_notification/models/access_controlled_action.py
lusid_notification/models/access_controlled_resource.py
lusid_notification/models/action_id.py
lusid_notification/models/amazon_sqs_notification_type.py
lusid_notification/models/amazon_sqs_notification_type_response.py
lusid_notification/models/amazon_sqs_principal_auth_notification_type.py
lusid_notification/models/amazon_sqs_principal_auth_notification_type_response.py
lusid_notification/models/attempt.py
lusid_notification/models/attempt_status.py
lusid_notification/models/azure_service_bus_notification_type.py
lusid_notification/models/azure_service_bus_type_response.py
lusid_notification/models/create_notification_request.py
lusid_notification/models/create_subscription.py
lusid_notification/models/delivery.py
lusid_notification/models/email_notification_type.py
lusid_notification/models/email_notification_type_response.py
lusid_notification/models/event_field_definition.py
lusid_notification/models/event_type_schema.py
lusid_notification/models/id_selector_definition.py
lusid_notification/models/identifier_part_schema.py
lusid_notification/models/link.py
lusid_notification/models/lusid_problem_details.py
lusid_notification/models/lusid_validation_problem_details.py
lusid_notification/models/manual_event.py
lusid_notification/models/manual_event_body.py
lusid_notification/models/manual_event_header.py
lusid_notification/models/manual_event_request.py
lusid_notification_sdk_preview-0.1.1056.dist-info/METADATA
lusid_notification_sdk_preview-0.1.1056.dist-info/WHEEL
lusid_notification_sdk_preview-0.1.1056.dist-info/top_level.txt
lusid_notification_sdk_preview-0.1.1056.dist-info/RECORD
